<?xml version="1.0"?>
<adm0 name="Armenia" code="AM">
    <adm1 code="AM01" name="Yerevan">
        <adm2 code="AM01001" name="Achapnyak"/>
        <adm2 code="AM01002" name="Avan"/>
        <adm2 code="AM01003" name="Arabkir"/>
        <adm2 code="AM01004" name="Davtashen"/>
        <adm2 code="AM01005" name="Erebuni"/>
        <adm2 code="AM01006" name="Kentron"/>
        <adm2 code="AM01007" name="Malatia-Sebastia"/>
        <adm2 code="AM01008" name="Nor Nork"/>
        <adm2 code="AM01009" name="Nork-Marash"/>
        <adm2 code="AM01010" name="Nubarashen"/>
        <adm2 code="AM01011" name="Shengavit"/>
        <adm2 code="AM01012" name="Qanaker-Zeytun"/>
    </adm1>
    <adm1 code="AM02" name="Aragatsotn">
        <!--        <adm2 code="AM021" name="Ashtarak"/>-->
        <!--        <adm2 code="AM024" name="Talin"/>-->
        <!--        <adm2 code="AM023" name="Aragats"/>-->
        <!--        <adm2 code="AM022" name="Aparan"/>-->
        <adm2 code="AM2001" name="Ashtarak"/>
        <adm2 code="AM02002" name="Aparan">
            <adm3 code="AM02002_01" name="Aparan"/>
            <adm3 code="AM02002_02" name="Aragats"/>
            <adm3 code="AM02002_03" name="Arayi"/>
            <adm3 code="AM02002_04" name="Apnagyugh"/>
            <adm3 code="AM02002_05" name="Yeghipatrush"/>
            <adm3 code="AM02002_06" name="Yernjatap"/>
            <adm3 code="AM02002_07" name="Ttujur"/>
            <adm3 code="AM02002_08" name="Lusagyugh"/>
            <adm3 code="AM02002_09" name="Tsaghkashen"/>
            <adm3 code="AM02002_10" name="Kayk"/>
            <adm3 code="AM02002_11" name="Hartavan"/>
            <adm3 code="AM02002_12" name="Dzoraglukh"/>
            <adm3 code="AM02002_13" name="Nigavan"/>
            <adm3 code="AM02002_14" name="Shenavan"/>
            <adm3 code="AM02002_15" name="Shoghakn"/>
            <adm3 code="AM02002_16" name="Chknagh"/>
            <adm3 code="AM02002_17" name="Jrambar"/>
            <adm3 code="AM02002_18" name="Saralanj"/>
            <adm3 code="AM02002_19" name="Vardenis"/>
            <adm3 code="AM02002_20" name="Vardenut"/>
            <adm3 code="AM02002_21" name="Kuchak"/>
        </adm2>
        <adm2 code="AM02003" name="Talin"/>
        <adm2 code="AM02004" name="Agarak"/>
        <adm2 code="AM02005" name="Agarakavan"/>
        <adm2 code="AM02006" name="Alagyaz">
            <adm3 code="AM02006_01" name="Alagyaz"/>
            <adm3 code="AM02006_02" name="Avshen"/>
            <adm3 code="AM02006_03" name="Kaniashir"/>
            <adm3 code="AM02006_04" name="Charchakis"/>
            <adm3 code="AM02006_05" name="Mi&#x575;natun"/>
            <adm3 code="AM02006_06" name="Mirak"/>
            <adm3 code="AM02006_07" name="Shenkani"/>
            <adm3 code="AM02006_08" name="Jamshlu"/>
            <adm3 code="AM02006_09" name="Ryataza"/>
            <adm3 code="AM02006_10" name="Sadunts"/>
            <adm3 code="AM02006_11" name="Sipan"/>
        </adm2>
        <adm2 code="AM02007" name="Akunk"/>
        <adm2 code="AM02008" name="Aghdzk"/>
        <adm2 code="AM02010" name="Antarut"/>
        <adm2 code="AM02011" name="Ashnak"/>
        <adm2 code="AM02012" name="Avan"/>
        <adm2 code="AM02013" name="Metsadzor"/>
        <adm2 code="AM02016" name="Aragatsavan">
            <adm3 code="AM02016_01" name="Aragatsavan"/>
            <adm3 code="AM02016_02" name="Arteni"/>
            <adm3 code="AM02016_03" name="Getap"/>
            <adm3 code="AM02016_04" name="Lusakn"/>
        </adm2>
        <adm2 code="AM02017" name="Aragatsotn"/>
        <adm2 code="AM02019" name="Tatul"/>
        <adm2 code="AM02020" name="Artashavan"/>
        <adm2 code="AM02022" name="Aruch"/>
        <adm2 code="AM02024" name="Bazmakhpyur"/>
        <adm2 code="AM02025" name="Otevan"/>
        <adm2 code="AM02026" name="Arevut"/>
        <adm2 code="AM02028" name="Byurakan"/>
        <adm2 code="AM02029" name="Garnahovit"/>
        <adm2 code="AM02034" name="Kanch"/>
        <adm2 code="AM02035" name="Dashtadem"/>
        <adm2 code="AM02036" name="Davtashen"/>
        <adm2 code="AM02038" name="Dian"/>
        <adm2 code="AM02039" name="Dprevank"/>
        <adm2 code="AM02041" name="Yeghnik"/>
        <adm2 code="AM02044" name="Zarinja"/>
        <adm2 code="AM02045" name="Zovasar"/>
        <adm2 code="AM02047" name="Tlik"/>
        <adm2 code="AM02048" name="Irind"/>
        <adm2 code="AM02050" name="Lernarot"/>
        <adm2 code="AM02053" name="Tsaghkahovit">
            <adm3 code="AM02053_01" name="Tsaghkahovit"/>
            <adm3 code="AM02053_02" name="Geghadir"/>
            <adm3 code="AM02053_03" name="Geghadzor"/>
            <adm3 code="AM02053_04" name="Gegharot"/>
            <adm3 code="AM02053_05" name="Lernapar"/>
            <adm3 code="AM02053_06" name="Berkarat"/>
            <adm3 code="AM02053_07" name="Tsilkar"/>
            <adm3 code="AM02053_08" name="Hnaberd"/>
            <adm3 code="AM02053_09" name="Norashen"/>
            <adm3 code="AM02053_10" name="Vardablur"/>
        </adm2>
        <adm2 code="AM02055" name="Tsaghkasar"/>
        <adm2 code="AM02057" name="Katnakhpyur"/>
        <adm2 code="AM02058" name="Karbi"/>
        <adm2 code="AM02059" name="Karmrashen"/>
        <adm2 code="AM02060" name="Kakavadzor"/>
        <adm2 code="AM02061" name="Kosh"/>
        <adm2 code="AM02062" name="Hako"/>
        <adm2 code="AM02064" name="Hatsashen"/>
        <adm2 code="AM02067" name="Ddmasar"/>
        <adm2 code="AM02068" name="Ghazaravan"/>
        <adm2 code="AM02069" name="Mastara"/>
        <adm2 code="AM02070" name="Melikgyugh"/>
        <adm2 code="AM02073" name="Nerkin Bazmaberd"/>
        <adm2 code="AM02074" name="Nerkin Sasnashen"/>
        <adm2 code="AM02076" name="Nor Amanos"/>
        <adm2 code="AM02079" name="Nor Artik"/>
        <adm2 code="AM02080" name="Nor Yedesia"/>
        <adm2 code="AM02081" name="Shamiram"/>
        <adm2 code="AM02084" name="Shgharshik"/>
        <adm2 code="AM02085" name="Vosketas"/>
        <adm2 code="AM02086" name="Voskehat"/>
        <adm2 code="AM02087" name="Voskevaz"/>
        <adm2 code="AM02089" name="Partizak"/>
        <adm2 code="AM02093" name="Saghmosavan"/>
        <adm2 code="AM02095" name="Sasunik"/>
        <adm2 code="AM02098" name="Sorik"/>
        <adm2 code="AM02099" name="Suser"/>
        <adm2 code="AM02103" name="Verin Bazmaberd"/>
        <adm2 code="AM02104" name="Verin Sasnashen"/>
        <adm2 code="AM02105" name="Verin Sasunik"/>
        <adm2 code="AM02106" name="Tegher"/>
        <adm2 code="AM02107" name="Tsamakasar"/>
        <adm2 code="AM02108" name="Ushi"/>
        <adm2 code="AM02109" name="Ujan"/>
        <adm2 code="AM02110" name="Parpi"/>
        <adm2 code="AM02112" name="Ohanavan"/>
        <adm2 code="AM02113" name="Oshakan"/>
        <adm2 code="AM02114" name="Orgov"/>
    </adm1>
    <adm1 code="AM03" name="Ararat">
        <adm2 code="AM031" name="Ararat"/>
        <adm2 code="AM033" name="Masis"/>
        <adm2 code="AM032" name="Artashat"/>
    </adm1>
    <adm1 code="AM04" name="Armavir">
        <adm2 code="AM04001" name="Armavir"/>
        <adm2 code="AM04002" name="Ejmiatsin  "/>
        <adm2 code="AM04003" name="Metsamor"/>
        <adm2 code="AM04004" name="Aknalich"/>
        <adm2 code="AM04005" name="Aknashen"/>
        <adm2 code="AM04006" name="Aghavnatun"/>
        <adm2 code="AM04007" name="Amasia"/>
        <adm2 code="AM04008" name="Amberd"/>
        <adm2 code="AM04009" name="Aygek"/>
        <adm2 code="AM04010" name="Aygeshat"/>
        <adm2 code="AM04011" name="Aygeshat"/>
        <adm2 code="AM04012" name="Apaga"/>
        <adm2 code="AM04013" name="Aratashen"/>
        <adm2 code="AM04014" name="Aragats"/>
        <adm2 code="AM04015" name="Arazap"/>
        <adm2 code="AM04016" name="Araks &#10;(Vagharshapat)"/>
        <adm2 code="AM04017" name="Araks(Armavir)"/>
        <adm2 code="AM04018" name="Argavand"/>
        <adm2 code="AM04019" name="Argina"/>
        <adm2 code="AM04020" name="Armavir v. "/>
        <adm2 code="AM04021" name="Arshaluys"/>
        <adm2 code="AM04022" name="Artamet"/>
        <adm2 code="AM04023" name="Artimet"/>
        <adm2 code="AM04024" name="Artashar"/>
        <adm2 code="AM04025" name="Arevadasht"/>
        <adm2 code="AM04026" name="Arevashat"/>
        <adm2 code="AM04027" name="Arevik"/>
        <adm2 code="AM04028" name="Bagaran"/>
        <adm2 code="AM04029" name="Baghramyan (Baghramyan)"/>
        <adm2 code="AM04030" name="Baghramyan (Vagharshapat) "/>
        <adm2 code="AM04031" name="Bambakashat"/>
        <adm2 code="AM04032" name="Berkashat"/>
        <adm2 code="AM04033" name="Gai"/>
        <adm2 code="AM04034" name="Getashen"/>
        <adm2 code="AM04035" name="Griboyedov"/>
        <adm2 code="AM04036" name="Dalarik"/>
        <adm2 code="AM04037" name="Dasht"/>
        <adm2 code="AM04038" name="Dokhs"/>
        <adm2 code="AM04039" name="Yeghegnut"/>
        <adm2 code="AM04040" name="Yeraskhahun"/>
        <adm2 code="AM04041" name="Yervandashat"/>
        <adm2 code="AM04042" name="Zartonk"/>
        <adm2 code="AM04043" name="Maisyan"/>
        <adm2 code="AM04044" name="Lenughi"/>
        <adm2 code="AM04045" name="Lernagog"/>
        <adm2 code="AM04046" name="Lernamerdz"/>
        <adm2 code="AM04047" name="Lukashin"/>
        <adm2 code="AM04048" name="Lusagyugh"/>
        <adm2 code="AM04049" name="Khanjian"/>
        <adm2 code="AM04050" name="Khoronk"/>
        <adm2 code="AM04051" name="Tsaghkalanj"/>
        <adm2 code="AM04052" name="Tsaghkunk"/>
        <adm2 code="AM04053" name="Tsiatsan"/>
        <adm2 code="AM04054" name="Koghbavan"/>
        <adm2 code="AM04055" name="Haytagh"/>
        <adm2 code="AM04056" name="Haykashen"/>
        <adm2 code="AM04057" name="Haykavan"/>
        <adm2 code="AM04058" name="Hatsik"/>
        <adm2 code="AM04059" name="Sardarapat"/>
        <adm2 code="AM04060" name="Hovtamech"/>
        <adm2 code="AM04061" name="Hushakert"/>
        <adm2 code="AM04062" name="Aygevan"/>
        <adm2 code="AM04063" name="Margara"/>
        <adm2 code="AM04064" name="Metsamor"/>
        <adm2 code="AM04065" name="Merdzavan"/>
        <adm2 code="AM04066" name="Myasnikyan"/>
        <adm2 code="AM04067" name="Mrgashat"/>
        <adm2 code="AM04068" name="Mrgastan"/>
        <adm2 code="AM04069" name="Musaler"/>
        <adm2 code="AM04070" name="Nalbandyan"/>
        <adm2 code="AM04071" name="Nor Armavir"/>
        <adm2 code="AM04072" name="Nor Artagers"/>
        <adm2 code="AM04073" name="Nor Kesaria"/>
        <adm2 code="AM04074" name="Norakert"/>
        <adm2 code="AM04075" name="Norapat"/>
        <adm2 code="AM04076" name="Noravan"/>
        <adm2 code="AM04077" name="Shahumyan"/>
        <adm2 code="AM04078" name="Shahumyan Poultry Plant"/>
        <adm2 code="AM04079" name="Shenavan"/>
        <adm2 code="AM04080" name="Shenik"/>
        <adm2 code="AM04081" name="Voskehat"/>
        <adm2 code="AM04082" name="Ptghunk"/>
        <adm2 code="AM04083" name="Janfida"/>
        <adm2 code="AM04084" name="Jrashen"/>
        <adm2 code="AM04085" name="Jrapat"/>
        <adm2 code="AM04086" name="Jrarpi"/>
        <adm2 code="AM04087" name="Geghakert"/>
        <adm2 code="AM04088" name="Alashkert"/>
        <adm2 code="AM04089" name="Vanand"/>
        <adm2 code="AM04090" name="Vardanashen"/>
        <adm2 code="AM04091" name="Talvorik"/>
        <adm2 code="AM04092" name="Tandzut"/>
        <adm2 code="AM04093" name="Taronik"/>
        <adm2 code="AM04094" name="Parakar"/>
        <adm2 code="AM04095" name="Pshatavan"/>
        <adm2 code="AM04096" name="Karakert"/>
        <adm2 code="AM04097" name="Ferik"/>
    </adm1>
    <adm1 code="AM05" name="Gegharkunik">
        <!--        <adm2 code="AM054" name="Sevan"/>-->
        <!--        <adm2 code="AM052" name="Karmir"/>-->
        <!--        <adm2 code="AM055" name="Vardenis"/>-->
        <!--        <adm2 code="AM051" name="Gavar"/>-->
        <!--        <adm2 code="AM053" name="Martuni"/>-->
        <adm2 code="AM05_01" name="Shoghakat">
            <adm3 code="AM05_0101" name="Shoghakat"/>
            <adm3 code="AM05_0102" name="Aghberk"/>
            <adm3 code="AM05_0103" name="Artanish"/>
            <adm3 code="AM05_0104" name="Drakhtik"/>
            <adm3 code="AM05_0105" name="Tsapatagh"/>
            <adm3 code="AM05_0106" name="Jil"/>
        </adm2>
        <adm2 code="AM05002" name="Chambarak">
            <adm3 code="AM05002_01" name="Chambarak"/>
            <adm3 code="AM05002_02" name="Aygut"/>
            <adm3 code="AM05002_03" name="Antaramej"/>
            <adm3 code="AM05002_04" name="Getik"/>
            <adm3 code="AM05002_05" name="Dprabak"/>
            <adm3 code="AM05002_06" name="Ttujur"/>
            <adm3 code="AM05002_07" name="Kalavan"/>
            <adm3 code="AM05002_08" name="Dzoravank"/>
            <adm3 code="AM05002_09" name="Martuni"/>
            <adm3 code="AM05002_10" name="Vahan"/>
        </adm2>
        <adm2 code="AM05005" name="Vardenis">
            <adm3 code="AM05005_01" name="Vardenis"/>
            <adm3 code="AM05005_02" name="Verin  Shorzha"/>
            <adm3 code="AM05005_03" name="Nerkin Shorzha"/>
            <adm3 code="AM05005_04" name="Ayrk"/>
        </adm2>
        <adm2 code="AM05023" name="Geghamasar">
            <adm3 code="AM05023_01" name="Geghamasar"/>
            <adm3 code="AM05023_02" name="Sotk"/>
            <adm3 code="AM05023_03" name="Azat"/>
            <adm3 code="AM05023_04" name="Avazan"/>
            <adm3 code="AM05023_05" name="Areguni"/>
            <adm3 code="AM05023_06" name="Arpunk"/>
            <adm3 code="AM05023_07" name="Geghamabak"/>
            <adm3 code="AM05023_08" name="Daranak"/>
            <adm3 code="AM05023_09" name="Kakhakn"/>
            <adm3 code="AM05023_10" name="Kut"/>
            <adm3 code="AM05023_11" name="Kutakan"/>
            <adm3 code="AM05023_12" name="Shatjrek"/>
            <adm3 code="AM05023_13" name="Shatvan"/>
            <adm3 code="AM05023_14" name="Jaghatsadzor"/>
            <adm3 code="AM05023_15" name="Tretuk"/>
            <adm3 code="AM05023_16" name="Pambak"/>
            <adm3 code="AM05023_17" name="Pokr Masrik"/>
        </adm2>
        <adm2 code="AM05007" name="Akhpradzor"/>
        <adm2 code="AM05008" name="Akunk"/>
        <adm2 code="AM05014" name="Avazan"/>
        <adm2 code="AM05013" name="Astghadzor"/>
        <adm2 code="AM05016" name="Artsvanist"/>
        <adm2 code="AM05020" name="Berdkunk"/>
        <adm2 code="AM05021" name="Gandzak"/>
        <adm2 code="AM05001" name="Gavar"/>
        <adm2 code="AM05024" name="Geghamavan"/>
        <adm2 code="AM05025" name="Gegharkunik"/>
        <adm2 code="AM05026" name="Geghakar"/>
        <adm2 code="AM05027" name="Geghhovit"/>
        <adm2 code="AM05030" name="Ddmashen"/>
        <adm2 code="AM05033" name="Yeranos"/>
        <adm2 code="AM05034" name="Zolakar"/>
        <adm2 code="AM05035" name="Zovaber"/>
        <adm2 code="AM05038" name="Lanjakhpyur"/>
        <adm2 code="AM05039" name="Lichk"/>
        <adm2 code="AM05040" name="Lchashen"/>
        <adm2 code="AM05042" name="Lchap"/>
        <adm2 code="AM05043" name="Lusakunk"/>
        <adm2 code="AM05044" name="Khachakhpyur"/>
        <adm2 code="AM05045" name="Tsakkar"/>
        <adm2 code="AM05046" name="Tsaghkashen"/>
        <adm2 code="AM05047" name="Tsaghkunk"/>
        <adm2 code="AM05049" name="Tsovagyugh"/>
        <adm2 code="AM05050" name="Tsovazard"/>
        <adm2 code="AM05051" name="Tsovak"/>
        <adm2 code="AM05036" name="Tsovasar"/>
        <adm2 code="AM05052" name="Tsovinar"/>
        <adm2 code="AM05055" name="Karchakhpyur"/>
        <adm2 code="AM05056" name="Karmirgyugh"/>
        <adm2 code="AM05059" name="Hayravank"/>
        <adm2 code="AM05060" name="Dzoragyugh"/>
        <adm2 code="AM05062" name="Madina"/>
        <adm2 code="AM05063" name="Martuni"/>
        <adm2 code="AM05064" name="Maqenis"/>
        <adm2 code="AM05065" name="Mets Masrik"/>
        <adm2 code="AM05066" name="Nerkin Getashen"/>
        <adm2 code="AM05069" name="Norakert"/>
        <adm2 code="AM05070" name="Norashen"/>
        <adm2 code="AM05071" name="Noratus"/>
        <adm2 code="AM05075" name="Chkalovka"/>
        <adm2 code="AM05078" name="Sarukhan"/>
        <adm2 code="AM05079" name="Semyonovka"/>
        <adm2 code="AM05082" name="Vaghashen"/>
        <adm2 code="AM05004" name="Sevan"/>
        <adm2 code="AM05083" name="Vanevan"/>
        <adm2 code="AM05084" name="Vardadzor"/>
        <adm2 code="AM05085" name="Vardenik"/>
        <adm2 code="AM05086" name="Varser"/>
        <adm2 code="AM05087" name="Verin Getashen"/>
        <adm2 code="AM05089" name="Torfavan"/>
    </adm1>
    <adm1 code="AM06" name="Lori">
        <adm2 code="AM063" name="Spitak"/>
        <!--        <adm2 code="AM061" name="Gugark"/>-->
        <!--        <adm2 code="AM065" name="Tashir"/>-->
        <adm2 code="AM064" name="Stepanavan">
            <adm3 code="AM064_01" name="Armanis"/>
            <adm3 code="AM064_02" name="Katnakhpyur"/>
            <adm3 code="AM064_03" name="Urasar"/>
        </adm2>
        <adm2 code="AM062" name="Tumanian"/>
        <adm2 code="AM06010" name="Aznvadzor"/>
        <adm2 code="AM06015" name="Antaramut"/>
        <adm2 code="AM06021" name="Arevashogh"/>
        <adm2 code="AM06029" name="Gyulagarak">
            <adm3 code="AM06029_01" name="Amrakits"/>
            <adm3 code="AM06029_02" name="Gargar"/>
            <adm3 code="AM06029_03" name="Kurtan"/>
            <adm3 code="AM06029_04" name="Hobardsi"/>
            <adm3 code="AM06029_05" name="Pushkino"/>
            <adm3 code="AM06029_06" name="Vardablur"/>
        </adm2>
        <adm2 code="AM06044" name="Lori Berd">
            <adm3 code="AM06044_01" name="Agarak"/>
            <adm3 code="AM06044_02" name="Bovadzor"/>
            <adm3 code="AM06044_03" name="Lejan"/>
            <adm3 code="AM06044_04" name="Koghes"/>
            <adm3 code="AM06044_05" name="Hovnanadzor"/>
            <adm3 code="AM06044_06" name="Yaghdan"/>
            <adm3 code="AM06044_07" name="Sverdlov"/>
            <adm3 code="AM06044_08" name="Urut"/>
        </adm2>
        <adm2 code="AM06059" name="Halavar"/>
        <adm2 code="AM06066" name="Dzoragyugh"/>
        <adm2 code="AM06075" name="Mets Parni"/>
        <adm2 code="AM06086" name="Shenavan"/>
        <adm2 code="AM06089" name="Chkalov"/>
        <adm2 code="AM06097" name="Sarahart"/>
        <adm2 code="AM06002" name="Alaverdi">
            <adm3 code="AM06002_01" name="Akori"/>
            <adm3 code="AM06002_02" name="Tsaghkashat"/>
            <adm3 code="AM06002_03" name="Kachachkut"/>
            <adm3 code="AM06002_04" name="Haghpat"/>
            <adm3 code="AM06002_05" name="Jiliza"/>
        </adm2>
        <adm2 code="AM06026" name="Antarashen"/>
        <adm2 code="AM06023" name="Bazum"/>
        <adm2 code="AM06030" name="Gogaran"/>
        <adm2 code="AM06033" name="Darpas"/>
        <adm2 code="AM06035" name="Dsegh"/>
        <adm2 code="AM06040" name="Lernantsk"/>
        <adm2 code="AM06042" name="Lernavan"/>
        <adm2 code="AM06046" name="Lusakhpyur"/>
        <adm2 code="AM06049" name="Tsaghkaber"/>
        <adm2 code="AM06061" name="Hartagyugh"/>
        <adm2 code="AM06068" name="Ghursali"/>
        <adm2 code="AM06074" name="Metsavan">
            <adm3 code="AM06074_01" name="Dzyunashogh"/>
            <adm3 code="AM06074_02" name="Mikhaylovka"/>
            <adm3 code="AM06074_03" name="Paghakhpyur"/>
        </adm2>
        <adm2 code="AM06087" name="Shirakamut"/>
        <adm2 code="AM06095" name="Jrashen"/>
        <adm2 code="AM06098" name="Saramech"/>
        <adm2 code="AM06107" name="Pambak"/>
        <adm2 code="AM06109" name="Karadzor"/>
        <adm2 code="AM06003" name="Akhtala">
            <adm3 code="AM06003_01" name="Akhtala"/>
            <adm3 code="AM06003_02" name="Village next to the health center"/>
            <adm3 code="AM06003_03" name="Bendik"/>
            <adm3 code="AM06003_04" name="Chotchkan"/>
            <adm3 code="AM06003_05" name="Mets Ayrum"/>
            <adm3 code="AM06003_06" name="Pokr Ayrum"/>
            <adm3 code="AM06003_07" name="Shamlugh"/>
            <adm3 code="AM06003_08" name="Neghots"/>
        </adm2>
        <adm2 code="AM06019" name="Arjut"/>
        <adm2 code="AM06028" name="Geghasar"/>
        <adm2 code="AM06031" name="Gugark"/>
        <adm2 code="AM06034" name="Debet"/>
        <adm2 code="AM06036" name="Yeghegnut"/>
        <adm2 code="AM06041" name="Lernapat"/>
        <adm2 code="AM06043" name="Lermontovo"/>
        <adm2 code="AM06047" name="Khnkoyan"/>
        <adm2 code="AM06052" name="Katnajur"/>
        <adm2 code="AM06065" name="Dzoraget"/>
        <adm2 code="AM06070" name="Margahovit"/>
        <adm2 code="AM06083" name="Nor Khachakap"/>
        <adm2 code="AM06084" name="Shahumyan"/>
        <adm2 code="AM06088" name="Shnogh">
            <adm3 code="AM06088_01" name="Teghut"/>
            <adm3 code="AM06088_02" name="Karkop"/>
        </adm2>
        <adm2 code="AM06096" name="Saralanj"/>
        <adm2 code="AM06100" name="Sarchapet">
            <adm3 code="AM06100_01" name="Apaven"/>
            <adm3 code="AM06100_02" name="Artsni"/>
            <adm3 code="AM06100_03" name="Dzoramut"/>
            <adm3 code="AM06100_04" name="Gogavan"/>
            <adm3 code="AM06100_05" name="Petrovka"/>
            <adm3 code="AM06100_06" name="Privolnoye"/>
            <adm3 code="AM06100_07" name="Norashen"/>
        </adm2>
        <adm2 code="AM06102" name="Vahagnadzor"/>
        <adm2 code="AM06103" name="Vahagni"/>
        <adm2 code="AM06001" name="Vanadzor"/>
        <adm2 code="AM06108" name="Karaberd"/>
        <adm2 code="AM06112" name="Odzun">
            <adm3 code="AM06112_01" name="Amoj"/>
            <adm3 code="AM06112_02" name="Aygehat"/>
            <adm3 code="AM06112_03" name="Ardvi"/>
            <adm3 code="AM06112_04" name="Arevatsag"/>
            <adm3 code="AM06112_05" name="Tsater"/>
            <adm3 code="AM06112_06" name="Karmir Aghek"/>
            <adm3 code="AM06112_07" name="Hagvi"/>
            <adm3 code="AM06112_08" name="Mghart"/>
        </adm2>
        <adm2 code="AM06_02" name="Tashir">
            <adm3 code="AM06_0201" name="Blagodarnoe"/>
            <adm3 code="AM06_0202" name="Dashtadem"/>
            <adm3 code="AM06_0203" name="Lernahovit"/>
            <adm3 code="AM06_0204" name="Katnarat"/>
            <adm3 code="AM06_0205" name="Medovka"/>
            <adm3 code="AM06_0206" name="Kruglaya Shishka"/>
            <adm3 code="AM06_0207" name="Meghvahovit"/>
            <adm3 code="AM06_0208" name="Noramut"/>
            <adm3 code="AM06_0209" name="Novoseltsovo"/>
            <adm3 code="AM06_0210" name="Saratovka"/>
            <adm3 code="AM06_0211" name="Getavan"/>
        </adm2>
        <adm2 code="AM06_03" name="Fioletovo"/>
    </adm1>
    <adm1 code="AM07" name="Kotayk">
        <!--        <adm2 code="AM072" name="Hrazdan"/>-->
        <!--        <adm2 code="AM073" name="Nairi"/>-->
        <!--        <adm2 code="AM071" name="Kotayk"/>-->
        <adm2 code="AM07002" name="Abovyan"/>
        <adm2 code="AM07013" name="Aramus"/>
        <adm2 code="AM07018" name="Balahovit"/>
        <adm2 code="AM07022" name="Geghadir"/>
        <adm2 code="AM07023" name="Geghashen"/>
        <adm2 code="AM07004" name="Yeghvard">
            <adm3 code="AM07004_01" name="Yeghvard"/>
            <adm3 code="AM07004_02" name="Bujakan"/>
            <adm3 code="AM07004_03" name="Zovuni"/>
            <adm3 code="AM07004_04" name="Zoravan"/>
            <adm3 code="AM07004_05" name="Aragyugh"/>
            <adm3 code="AM07004_06" name="Saralanj"/>
        </adm2>
        <adm2 code="AM07005" name="Tsaghkadzor"/>
        <adm2 code="AM07041" name="Hatsavan"/>
        <adm2 code="AM07045" name="Meghradzor">
            <adm3 code="AM07045_01" name="Meghradzor"/>
            <adm3 code="AM07045_02" name="Aghavnadzor"/>
            <adm3 code="AM07045_03" name="Artavaz"/>
            <adm3 code="AM07045_04" name="Hankavan"/>
            <adm3 code="AM07045_05" name="Marmarik"/>
            <adm3 code="AM07045_06" name="Gorgoch"/>
            <adm3 code="AM07045_07" name="Pyunik"/>
        </adm2>
        <adm2 code="AM07048" name="Nor Geghi"/>
        <adm2 code="AM07052" name="Voghjaberd"/>
        <adm2 code="AM07054" name="Ptghni"/>
        <adm2 code="AM07060" name="Solak"/>
        <adm2 code="AM07064" name="Kanakeravan"/>
        <adm2 code="AM07009" name="Akunk">
            <adm3 code="AM07009_01" name="Akunk"/>
            <adm3 code="AM07009_02" name="Zovashen"/>
            <adm3 code="AM07009_03" name="Zar"/>
            <adm3 code="AM07009_04" name="Kaputan"/>
            <adm3 code="AM07009_05" name="Hatis"/>
            <adm3 code="AM07009_06" name="Kotayk"/>
            <adm3 code="AM07009_07" name="Nor gyugh"/>
            <adm3 code="AM07009_08" name="Sevaberd"/>
        </adm2>
        <adm2 code="AM07007" name="Charentsavan">
            <adm3 code="AM07007_01" name="Charentsavan"/>
            <adm3 code="AM07007_02" name="Alapars"/>
            <adm3 code="AM07007_03" name="Arzakan"/>
            <adm3 code="AM07007_04" name="Bjni"/>
            <adm3 code="AM07007_05" name="Karenis"/>
            <adm3 code="AM07007_06" name="Fantan"/>
        </adm2>
        <adm2 code="AM07014" name="Argel"/>
        <adm2 code="AM07003" name="Byureghavan">
            <adm3 code="AM07003_01" name="Byureghavan"/>
            <adm3 code="AM07003_02" name="Nurnus"/>
            <adm3 code="AM07003_03" name="Jraber"/>
        </adm2>
        <adm2 code="AM07058" name="Getargel"/>
        <adm2 code="AM07032" name="Teghenik"/>
        <adm2 code="AM07034" name="Katnakhpyur"/>
        <adm2 code="AM07001" name="Hrazdan"/>
        <adm2 code="AM07046" name="Mrgashen"/>
        <adm2 code="AM07050" name="Nor Yerznka"/>
        <adm2 code="AM07062" name="Verin Ptghni"/>
        <adm2 code="AM07065" name="Kasakh"/>
        <adm2 code="AM07011" name="Arinj"/>
        <adm2 code="AM07016" name="Arzni"/>
        <adm2 code="AM07021" name="Garni"/>
        <adm2 code="AM07026" name="Goght"/>
        <adm2 code="AM07033" name="Lernanist"/>
        <adm2 code="AM07035" name="Kamaris"/>
        <adm2 code="AM07043" name="Mayakovski"/>
        <adm2 code="AM07047" name="Nor Artamet"/>
        <adm2 code="AM07006" name="Nor Hachn"/>
        <adm2 code="AM07053" name="Proshyan"/>
        <adm2 code="AM07057" name="Jrvezh">
            <adm3 code="AM07057_01" name="Jrvezh"/>
            <adm3 code="AM07057_02" name="Zovk"/>
            <adm3 code="AM07057_03" name="Dzorakhpyur"/>
        </adm2>
        <adm2 code="AM07063" name="Kaghsi"/>
        <adm2 code="AM07066" name="Karashamb"/>
    </adm1>
    <adm1 code="AM08" name="Shirak">
        <!--        <adm2 code="AM084" name="Ashotsk"/>-->
        <!--        <adm2 code="AM082" name="Amasia"/>-->
        <!--        <adm2 code="AM081" name="Akhuryan"/>-->
        <adm2 code="AM083" name="Ani"/>
        <!--        <adm2 code="AM085" name="Artik"/>-->
        <adm2 code="AM08001" name="Gyumri"/>
        <adm2 code="AM08028" name="Arpi"/>
        <adm2 code="AM08016" name="Arapi"/>
        <adm2 code="AM08023" name="Bayandur"/>
        <adm2 code="AM08031" name="Getap"/>
        <adm2 code="AM08037" name="Yerazgavors"/>
        <adm2 code="AM08060" name="Haykasar"/>
        <adm2 code="AM08063" name="Harich"/>
        <adm2 code="AM08076" name="Gharibjanyan"/>
        <adm2 code="AM08086" name="Nahapetavan"/>
        <adm2 code="AM08093" name="Pemzashen"/>
        <adm2 code="AM08105" name="Saratak"/>
        <adm2 code="AM08111" name="Tufashen"/>
        <adm2 code="AM08004" name="Azatan"/>
        <adm2 code="AM08007" name="Akhuryan"/>
        <adm2 code="AM08014" name="Anushavan"/>
        <adm2 code="AM08002" name="Artik"/>
        <adm2 code="AM08027" name="Beniamin"/>
        <adm2 code="AM08032" name="Getk"/>
        <adm2 code="AM08046" name="Lernakert"/>
        <adm2 code="AM08061" name="Haykavan"/>
        <adm2 code="AM08067" name="Horom"/>
        <adm2 code="AM08078" name="Marmashen"/>
        <adm2 code="AM08087" name="Nor Kyank"/>
        <adm2 code="AM08102" name="Saralanj"/>
        <adm2 code="AM08107" name="Spandaryan"/>
        <adm2 code="AM08113" name="Panik"/>
        <adm2 code="AM08006" name="Akhurik"/>
        <adm2 code="AM08010" name="Amasia"/>
        <adm2 code="AM08015" name="Ashotsk"/>
        <adm2 code="AM08021" name="Arevshat"/>
        <adm2 code="AM08030" name="Geghanist"/>
        <adm2 code="AM08062" name="Hayrenyats"/>
        <adm2 code="AM08069" name="Hovtashen"/>
        <adm2 code="AM08079" name="Mets Mantash"/>
        <adm2 code="AM08083" name="Meghrashen"/>
        <adm2 code="AM08092" name="Voskehask"/>
        <adm2 code="AM08104" name="Sarapat"/>
        <adm2 code="AM08110" name="Vardakar"/>
        <adm2 code="AM08115" name="Pokr Mantash"/>
    </adm1>
    <adm1 code="AM09" name="Syunik">
        <adm2 code="AM093" name="Meghri"/>
        <adm2 code="AM092" name="Kapan"/>
        <adm2 code="AM091" name="Goris"/>
        <adm2 code="AM094" name="Sisian"/>
    </adm1>
    <adm1 code="AM10" name="Vayots Dzor">
        <adm2 code="AM102" name="Vayk"/>
        <adm2 code="AM101" name="Yeghegnadzor"/>
    </adm1>
    <adm1 code="AM11" name="Tavush">
        <adm2 code="AM113" name="Tavush"/>
        <adm2 code="AM112" name="Noyemberyan"/>
        <adm2 code="AM114" name="Dilidjan"/>
        <adm2 code="AM111" name="Idjevan"/>
    </adm1>
</adm0>
